plotrsdk/__init__.py
plotrsdk/books.py
plotrsdk/chapters.py
plotrsdk/characters.py
plotrsdk/movies.py
plotrsdk/quotes.py
plotrsdk/service.py
plotrsdk/utils.py
plotrsdk-1.0.7.dist-info/LICENSE.md
plotrsdk-1.0.7.dist-info/METADATA
plotrsdk-1.0.7.dist-info/WHEEL
plotrsdk-1.0.7.dist-info/top_level.txt
plotrsdk-1.0.7.dist-info/RECORD
