Metadata-Version: 2.1
Name: plotrsdk
Version: 1.0.7
Summary: A Python SDK for the Lord of the Rings API
Home-page: https://github.com/prabhumarappan/prabhu-lotr-SDK
Author: Prabhu Marappan
Author-email: prabhum.794@gmail.com
Requires-Python: >=3.6
License-File: LICENSE.md
